shapelets_native/__init__.py
shapelets_native/__init__.pyi
shapelets_native/_shapelets_extension.cp312-win_amd64.pyd
shapelets_native/_version.py
shapelets_native/_version.pyi
shapelets_native/py.typed
shapelets_native-2.2.6.dist-info/LICENSE.md
shapelets_native-2.2.6.dist-info/METADATA
shapelets_native-2.2.6.dist-info/WHEEL
shapelets_native-2.2.6.dist-info/top_level.txt
shapelets_native-2.2.6.dist-info/RECORD
