Metadata-Version: 2.1
Name: shapelets_native
Version: 2.2.6
Summary: Python native bindings
Home-page: https://shapelets.io
Author: Shapelets.io
Author-email: dev@shapelets.io
Classifier: Programming Language :: Python :: 3
Classifier: Operating System :: OS Independent
Classifier: License :: Other/Proprietary License
Requires-Python: >=3.8
License-File: LICENSE.md
